{
  "reply_must_include_website___ask_for_specific_needs_on_new_unclear_inquiry": "new_unclear_inquiry_include_website",
  "same_question_repeated___same_key_detail_asked_multiple_times": "no_reask_known_part_or_vin",
  "三段式信息收集": "lock_which_what_first",
  "三段式信息收集_-_must_ask_quantity_before_price": "ask_quantity_before_price",
  "三段式信息收集_-_what段_需求": "lock_which_what_first",
  "三段式信息收集_-_成交三要素_-_需求越具体信心越强": "lock_which_what_first",
  "三段式信息收集_-_第一段_锁定_which___what": "lock_which_what_first",
  "三段式信息收集_-_第一段锁定_which___what": "lock_which_what_first",
  "三段式信息收集_-_锁定_which___what": "lock_which_what_first",
  "三段式信息收集_5w2h_按依赖关系分阶段_不是平铺问一遍__-_第一段_锁定_which___what": "lock_which_what_first",
  "三段式信息收集___第一段_锁定_which___what": "lock_which_what_first",
  "三段式信息收集___身份与_vin": "lock_which_what_first",
  "三段式信息收集__第一段锁定_which___what_建议": "lock_which_what_first",
  "三段式信息收集_第一段_锁定___which优先级": "lock_which_what_first",
  "三段式信息收集_第一段_锁定_which___what": "lock_which_what_first",
  "三段式信息收集_第一段_锁定_which___what__and_禁止重复问需求": "lock_which_what_first",
  "三段式信息收集_第一段_锁定_which___what__和_整体销售思路": "lock_which_what_first",
  "三段式信息收集_第一段_锁定_which_what____身份与_vin": "lock_which_what_first",
  "不能重复使用等待话术": "no_repeat_wait_phrases",
  "不要等客户问才说__第一次回复_团队在确认价格_时_顺带说清楚这是中国发货_需要海运": "disclose_china_stock_and_sea_freight",
  "不重复问已有配件需求_也要先获取_vin_或_year_engine_code_后才能报价": "qualify_before_price",
  "严禁随意甩人工电话号码_054_913_5916": "no_leak_staff_phone",
  "价格与单位": "quote_with_currency_unit",
  "价格与单位_-_报价必须带货币单位": "quote_with_currency_unit",
  "价格与单位_-_报价必须带货币单位_p0": "quote_with_currency_unit",
  "价格与单位___报价顺序": "quote_with_currency_unit",
  "同一对话里不要用等待话术重复表达同一个意思": "no_repeat_wait_phrases",
  "声音": "no_exclamation_spam",
  "声音_-_不用感叹号": "no_exclamation_spam",
  "声音_-_不用条感叹号_短句_禁止客服过于生硬": "no_exclamation_spam",
  "声音_-_不要冷淡重复回复无变化内容": "no_repeat_wait_phrases",
  "声音_-_不要多余官网链接": "prefer_detail_url_over_homepage",
  "声音_-_同一对话里不要用_still_checking___still_waiting_反复表达同一个意思": "no_repeat_wait_phrases",
  "声音_-_新客户___模糊开场___必须带网站___问需求": "new_unclear_inquiry_include_website",
  "声音_-_禁止开场__great_news": "avoid_banned_opening_phrases",
  "声音_-_禁止开场_hi_there": "avoid_banned_opening_phrases",
  "声音___像真人_whatsapp_不像客服机器人": "whatsapp_email_tone",
  "声音___新客户___模糊开场___必须带网站___问需求": "new_unclear_inquiry_include_website",
  "官网首页链接限制___第3次发官网首页链接后禁止继续发": "website_spam",
  "客套话简短回应_不用每次都加尾巴": "short_courtesy_reply",
  "客户自我介绍_报姓名_时_像人类一样欢迎___自我介绍自己是_鲁子敬__不要跳过寒暄直接推销": "welcome_self_intro_as_luzijing",
  "客户说_谢谢_这类客套话_简短对应一句就行": "short_courtesy_reply",
  "成交三段式信息收集___成交三要素_需求越具体": "lock_which_what_first",
  "成交三要素___三段式信息收集": "lock_which_what_first",
  "成交三要素___报价___交易条件被客户接受后": "lock_which_what_first",
  "成交三要素___第三段_成交___三段式信息收集-数量": "lock_which_what_first",
  "成交三要素_信心是累积的___需求越具体": "lock_which_what_first",
  "报价___交易条件被客户接受后": "ask_quantity_before_price",
  "报价前_或报价同一轮_必须先问数量": "ask_quantity_before_price",
  "报价前先要_vin_或_year_engine_code": "qualify_before_price",
  "报价前先要_vin_或_year_engine_code_p0_must_qualify_before_price": "qualify_before_price",
  "报价前先要_vin_或_year_engine_code_p0_结构化旗标__must_qualify_before_price": "qualify_before_price",
  "报价前先要_vin_或_year_engine_code_p0_结构化旗标_must_qualify_before_price": "qualify_before_price",
  "报价前先要_vin_或_year_engine_code_报价必须带货币单位_p0": "quote_with_currency_unit",
  "报价前先要_vin_或_year_engine_code_禁止直接说去跟团队确认价格_库存": "qualify_before_price",
  "报价必须带货币单位_p0": "quote_with_currency_unit",
  "报价必须带货币单位_p0____报价前先要_vin_或_year_engine_code_p0_must_qualify_before_price": "quote_with_currency_unit",
  "整体销售思路_-_三段式信息收集_-_需求越具体_信心越高": "lock_which_what_first",
  "整体销售思路_-_三段式信息收集_第一段_锁定_-_which___what": "lock_which_what_first",
  "整体销售思路_-_不能直接回答价格包含运输与关税_需先确认车辆识别信息": "lock_which_what_first",
  "整体销售思路_-_必须英文口语短消息": "lock_which_what_first",
  "整体销售思路_-_报价前先要_vin_或_model_year_engine_code_不要机械应付转发官网首页链接": "qualify_before_price",
  "整体销售思路_-_报价前先要_vin_或_model_year_engine_code_报价必须带货币单位": "quote_with_currency_unit",
  "整体销售思路_报价前先要_vin_或_year_engine_code_must_qualify_before_price__禁止直接说去跟团队确认价格_先问身": "qualify_before_price",
  "新客户___模糊开场___必须带网站___问需求": "new_unclear_inquiry_include_website",
  "永久不要_编造_已核实___已检查__p0": "no_fake_verified_claim",
  "永远不要_-_禁止编造_已核实___已检查__p0": "no_fake_verified_claim",
  "永远不要暴露翻译软件___ocr___内部工具___审批流程": "no_expose_internal_tools",
  "永远不要编造库存_价格_交期_付款_地址": "no_invent_price_or_stock",
  "禁止使用_still_checking___still_waiting_这类等待话术反复表达同一个意思": "no_repeat_wait_phrases",
  "禁止使用同一轮对话里重复表达等待话术": "no_repeat_wait_phrases",
  "禁止使用等待话术": "no_repeat_wait_phrases",
  "禁止反复等待话术": "no_repeat_wait_phrases",
  "禁止多次重复同类等待话术": "no_repeat_wait_phrases",
  "禁止开场__hi_there": "avoid_banned_opening_phrases",
  "禁止编造_已核实___已检查__p0": "no_fake_verified_claim",
  "禁止编造价格_价格单位必须带单位": "quote_with_currency_unit",
  "禁止编造价格数字": "no_invent_price_or_stock",
  "禁止编造库存_价格_交期_付款_地址": "no_invent_price_or_stock",
  "禁止重复等待话术": "no_repeat_wait_phrases",
  "禁止重复表达同一等待话术": "no_repeat_wait_phrases",
  "禁止随意甩人工电话号码_054_913_5916": "no_leak_staff_phone",
  "第一段_锁定_which___what": "lock_which_what_first",
  "第一段_锁定_which___what____声音": "lock_which_what_first",
  "第一段_锁定_which___what_优先采用vin或车型年份发动机代码_避免死等vin或反复问同一问题": "lock_which_what_first",
  "第三段_成交": "ask_quantity_before_price",
  "网站目录里的货源都在中国_我们做的是定制拆解___按需发货_海运为主__不是加纳本地现货": "disclose_china_stock_and_sea_freight",
  "要铭牌_vin_照片_不是随便一张车照_p0": "ask_plate_not_generic_photo",
  "要铭牌_vin_照片_不是随便一张车照_p0___同一对话里不要重复同一句要求拍_vin": "ask_plate_not_generic_photo",
  "身份与_vin": "no_reask_known_part_or_vin",
  "身份与_vin_-_报价前先要_vin_或_year_engine_code": "qualify_before_price",
  "身份与_vin_-_报价前先要_vin_或_year_engine_code_p0_结构化旗标_must_qualify_before_price": "qualify_before_price",
  "身份与_vin_-_要铭牌_vin_照片_不是随便一张车照_p0__确认车辆信息不要重复问已知需求": "ask_plate_not_generic_photo",
  "身份与_vin___三段式信息收集": "lock_which_what_first",
  "身份与_vin___三段式信息收集_-_which": "lock_which_what_first",
  "身份与_vin___三段式信息收集___三段式信息收集_-_what": "lock_which_what_first",
  "身份与_vin___不止_vin_场景": "no_reask_known_part_or_vin",
  "身份与_vin___报价前先要_vin_或_year_engine_code": "qualify_before_price",
  "身份与_vin___锁定第一段信息收集": "lock_which_what_first",
  "身份与_vin___需求确认": "no_reask_known_part_or_vin",
  "身份与_vin__客户给的_vin_车台号_铭牌_当作已确认事实保存_后续禁止再问_vin_禁止重置": "ask_plate_not_generic_photo",
  "身份与_vin__报价前先要_vin_或_year_engine_code_must_qualify_before_price": "qualify_before_price",
  "重复等待话术": "no_repeat_wait_phrases"
}
